bobj/__init__.py
bobj/category.py
bobj/core.py
bobj/folders.py
bobj/groups.py
bobj/instances.py
bobj/login.py
bobj/publications.py
bobj/support.py
bobj/users.py
bobj-0.145.dist-info/METADATA
bobj-0.145.dist-info/WHEEL
bobj-0.145.dist-info/top_level.txt
bobj-0.145.dist-info/RECORD
