Metadata-Version: 2.1
Name: bobj
Version: 0.145
Summary: A comprehensive toolkit designed to streamline tasks for SAP Business Objects administrators.
Author: Rajat Gupta
Author-email: rajatgupta.1988@gmail.com
Requires-Dist: requests (>=2.25)
